pigz.cpython-37m-x86_64-linux-gnu.so
pigz-2.9rc3.dist-info/METADATA
pigz-2.9rc3.dist-info/WHEEL
pigz-2.9rc3.dist-info/top_level.txt
pigz-2.9rc3.dist-info/RECORD
