Metadata-Version: 2.1
Name: pigz
Version: 2.9rc3
Summary: pigz - python bindings to pigz (parallel gzip)
Author-email: Pigz Developers <noreply@email.com>
Maintainer-email: Thamme Gowda <tgowdan@gmail.com>
Project-URL: homepage, https://github.com/thammegowda/pigz
Project-URL: documentation, https://github.com/thammegowda/pigz
Project-URL: repository, https://github.com/thammegowda/pigz
Classifier: Development Status :: 4 - Beta
Classifier: Programming Language :: Python :: 3 :: Only
Classifier: Programming Language :: Python :: 3.7
Classifier: Programming Language :: Python :: 3.8
Classifier: Programming Language :: Python :: 3.9
Classifier: Programming Language :: Python :: 3.10
Classifier: Programming Language :: Python :: 3.11
Requires-Python: >=3.7
Provides-Extra: test
Requires-Dist: pytest ; extra == 'test'
